<Shade>
            <Node>
                <UI>DropDown</UI>
                <Items>SubBusiness|Month|Gross;hell|esef|awdwa;4|5|6;7|8|9</Items>
                <Cols>
                    <Col>
                        <Name>SubBusiness</Name>
                        <DisplayOnSelect>Y</DisplayOnSelect>
                        <vSelectPath>Test.selected</vSelectPath>
                    </Col>
                    <Col>
                        <Name>Month</Name>
                        <DisplayOnSelect>N</DisplayOnSelect>
                    </Col>
                    <Col>
                        <Name>Gross</Name>
                        <DisplayOnSelect>N</DisplayOnSelect>
                    </Col>
                </Cols>
            </Node>
</Shade> 
   